bmagick/__init__.py
bmagick/magick.py
bmagick-0.2.0.dist-info/METADATA
bmagick-0.2.0.dist-info/RECORD
bmagick-0.2.0.dist-info/WHEEL
bmagick-0.2.0.dist-info/top_level.txt
