Metadata-Version: 2.1
Name: bmagick
Version: 0.2.0
Summary: Python interface to ImageMagick or GraphicsMagick
Home-page: https://github.com/BlackEarth/bmagick
Author: Sean Harrison
Author-email: sah@bookgenesis.com
License: MPL 2.0
Platform: UNKNOWN
Classifier: Development Status :: 1 - Planning
Classifier: Intended Audience :: Developers
Classifier: License :: OSI Approved :: Mozilla Public License 2.0 (MPL 2.0)
Classifier: Programming Language :: Python :: 2
Classifier: Programming Language :: Python :: 3
Provides-Extra: test
Provides-Extra: dev
Provides-Extra: dev
Requires-Dist: twine; extra == 'dev'
Provides-Extra: test
